freac
