Metadata-Version: 1.0
Name: freac
Version: 2016.11.16
Summary: Converter from Frelon to Crysalis
Home-page: https://hg.3lp.cx/id11tb
Author: Vadim Dyadkin
Author-email: dyadkin@gmail.com
License: GPLv3
Platform: UNKNOWN
